LICENSE
README.md
nonebot_plugin_al/__init__.py
nonebot_plugin_al/api.py
nonebot_plugin_al/bili.py
nonebot_plugin_al/config.py
nonebot_plugin_al/data/eq.json
nonebot_plugin_al/data/ship.json
nonebot_plugin_al/draw.py
nonebot_plugin_al/name.py
nonebot_plugin_al/send_message.py
nonebot_plugin_al/utils.py
nonebot_plugin_al-0.3.10.dist-info/LICENSE
nonebot_plugin_al-0.3.10.dist-info/METADATA
nonebot_plugin_al-0.3.10.dist-info/WHEEL
nonebot_plugin_al-0.3.10.dist-info/RECORD
