Metadata-Version: 2.1
Name: nonebot-plugin-al
Version: 0.3.10
Summary: Azuer L plugin for NoneBot2
Home-page: https://github.com/Agnes4m/nonebot_plugin_AL
License: MIT
Keywords: game,nonebot2,plugin,bilibili
Author: Agnes_Digital
Author-email: Z735803792@163.com
Requires-Python: >=3.9,<4.0
Classifier: License :: OSI Approved :: MIT License
Classifier: Operating System :: OS Independent
Classifier: Programming Language :: Python
Classifier: Programming Language :: Python :: 3
Classifier: Programming Language :: Python :: 3.9
Classifier: Programming Language :: Python :: 3.10
Classifier: Programming Language :: Python :: 3.11
Requires-Dist: aiofiles (>=23.1.0,<24.0.0)
Requires-Dist: aiohttp (>=3.8.3)
Requires-Dist: bs4 (>=0.0.1,<0.0.2)
Requires-Dist: imgkit (>=1.2.3,<2.0.0)
Requires-Dist: nonebot-adapter-onebot (>=2.2.1)
Requires-Dist: nonebot2 (>=2.0.0,<3.0.0)
Requires-Dist: nonebot_plugin_htmlrender (>=0.2.0.3,<0.3.0.0)
Requires-Dist: opencv-python (>=4.7.0,<5.0.0)
Requires-Dist: pillow (>=9.5.0,<10.0.0)
Requires-Dist: pypinyin (>=0.49.0,<0.50.0)
Requires-Dist: ruamel.yaml (>=0.17.21,<0.18.0)
Project-URL: Repository, https://github.com/Agnes4m/nonebot_plugin_AL
